remote_hub/__init__.py
remote_hub/config_routes.py
remote_hub/ssh_to_server.py
remote_hub/transfer.py
remote_hub-0.2.2.dist-info/METADATA
remote_hub-0.2.2.dist-info/WHEEL
remote_hub-0.2.2.dist-info/entry_points.txt
remote_hub-0.2.2.dist-info/RECORD
